clerks_friend/__init__.py
clerks_friend/cli.py
clerks_friend/py.typed
clerks_friend/reports.py
clerks_friend/types.py
clerks_friend/utils.py
clerks_friend-1.1.2.dist-info/LICENSE
clerks_friend-1.1.2.dist-info/METADATA
clerks_friend-1.1.2.dist-info/WHEEL
clerks_friend-1.1.2.dist-info/entry_points.txt
clerks_friend-1.1.2.dist-info/RECORD
