Metadata-Version: 2.3
Name: clerks-friend
Version: 1.1.2
Summary: Useful reports for Ward Clerk's of The Church of Jesus Christ of Latter-Day Saints
License: MIT
Keywords: lcr,churchofjesuschrist
Author: Isaac Wagner
Author-email: 14634+IsaacsLab42@users.noreply.github.com
Requires-Python: >=3.10,<4.0
Classifier: Development Status :: 5 - Production/Stable
Classifier: Environment :: Console
Classifier: Intended Audience :: Developers
Classifier: Intended Audience :: Religion
Classifier: License :: OSI Approved :: MIT License
Classifier: Natural Language :: English
Classifier: Operating System :: OS Independent
Classifier: Programming Language :: Python :: 3
Classifier: Programming Language :: Python :: 3.10
Classifier: Programming Language :: Python :: 3.11
Classifier: Programming Language :: Python :: 3.12
Classifier: Programming Language :: Python :: 3.13
Classifier: Topic :: Religion
Requires-Dist: arrow (>=1.3.0,<2.0.0)
Requires-Dist: lcr-session (>=1.2.0,<2.0.0)
Requires-Dist: prettytable (>=3.10.2,<4.0.0)
Requires-Dist: python-dotenv (>=1.0.1,<2.0.0)
Requires-Dist: pyyaml (>=6.0.2,<7.0.0)
Requires-Dist: requests (>=2.32.3,<3.0.0)
Project-URL: Bug Tracker, https://github.com/IsaacsLab42/clerks_friend/issues
Project-URL: Documentation, https://clerks-friend.readthedocs.io/en/stable/
Project-URL: Homepage, https://github.com/IsaacsLab42/clerks_friend
Project-URL: Repository, https://github.com/IsaacsLab42/clerks_friend
